{"v":"5.9.0","fr":25,"ip":0,"op":43,"w":1080,"h":1080,"nm":"logo loading","ddd":0,"assets":[],"layers":[{"ddd":0,"ind":1,"ty":4,"nm":"Logo%20loading Outlines","sr":1,"ks":{"o":{"a":0,"k":100,"ix":11},"r":{"a":0,"k":0,"ix":10},"p":{"a":0,"k":[540,540,0],"ix":2,"l":2},"a":{"a":0,"k":[540,675,0],"ix":1,"l":2},"s":{"a":0,"k":[131,131,100],"ix":6,"l":2}},"ao":0,"shapes":[{"ty":"gr","it":[{"ind":0,"ty":"sh","ix":1,"ks":{"a":0,"k":{"i":[[0,0],[0,0],[0,0],[6.494,0],[0,0],[0,0],[-4.983,0],[-2.266,1.452],[0,0],[0,0],[11.478,0],[0,21.925],[0,0],[-4.53,3.63],[-4.833,0],[0,0]],"o":[[0,0],[0,0],[0,6.244],[0,0],[0,0],[0,6.534],[5.738,0],[0,0],[0,0],[0,7.405],[-15.252,0],[0,0],[0,-6.97],[3.474,-2.759],[0,0],[0,0]],"v":[[2.039,-30.856],[22.728,-30.856],[22.728,-21.854],[10.647,-10.673],[1.889,-10.673],[1.889,20.546],[10.496,29.694],[21.219,27.08],[21.974,27.08],[21.974,37.244],[4.455,50.312],[-22.728,21.272],[-22.728,-30.275],[-14.422,-45.667],[-1.887,-50.312],[2.039,-50.312]],"c":true},"ix":2},"nm":"Path 1","mn":"ADBE Vector Shape - Group","hd":false},{"ty":"fl","c":{"a":0,"k":[1,0.839860265395,0.169323191923,1],"ix":4},"o":{"a":0,"k":100,"ix":5},"r":1,"bm":0,"nm":"Fill 1","mn":"ADBE Vector Graphic - Fill","hd":false},{"ty":"tr","p":{"a":0,"k":[786.811,665.853],"ix":2},"a":{"a":0,"k":[0,0],"ix":1},"s":{"a":0,"k":[100,100],"ix":3},"r":{"a":0,"k":0,"ix":6},"o":{"a":0,"k":100,"ix":7},"sk":{"a":0,"k":0,"ix":4},"sa":{"a":0,"k":0,"ix":5},"nm":"Transform"}],"nm":"Group 1","np":2,"cix":2,"bm":0,"ix":1,"mn":"ADBE Vector Group","hd":false},{"ty":"gr","it":[{"ind":0,"ty":"sh","ix":1,"ks":{"a":0,"k":{"i":[[0,0],[3.775,0],[0,-11.035],[0,0],[0,0],[0,10.599],[0,0],[-16.159,0],[0,-7.115],[0,0]],"o":[[-2.567,-1.307],[-5.89,0],[0,0],[0,0],[-9.363,0],[0,0],[0,-20.183],[12.233,0],[0,0],[0,0]],"v":[[20.992,-18.586],[11.327,-20.62],[2.266,-7.26],[2.266,40.948],[-5.889,40.948],[-22.35,25.702],[-22.35,-10.31],[4.682,-40.948],[22.351,-27.88],[22.351,-18.586]],"c":true},"ix":2},"nm":"Path 1","mn":"ADBE Vector Shape - Group","hd":false},{"ty":"fl","c":{"a":0,"k":[1,0.839860265395,0.169323191923,1],"ix":4},"o":{"a":0,"k":100,"ix":5},"r":1,"bm":0,"nm":"Fill 1","mn":"ADBE Vector Graphic - Fill","hd":false},{"ty":"tr","p":{"a":0,"k":[733.881,673.912],"ix":2},"a":{"a":0,"k":[0,0],"ix":1},"s":{"a":0,"k":[100,100],"ix":3},"r":{"a":0,"k":0,"ix":6},"o":{"a":0,"k":100,"ix":7},"sk":{"a":0,"k":0,"ix":4},"sa":{"a":0,"k":0,"ix":5},"nm":"Transform"}],"nm":"Group 2","np":2,"cix":2,"bm":0,"ix":2,"mn":"ADBE Vector Group","hd":false},{"ty":"gr","it":[{"ind":0,"ty":"sh","ix":1,"ks":{"a":0,"k":{"i":[[0,0],[0,0],[0,-5.663],[-5.889,0],[0,8.422]],"o":[[0,0],[-8.759,0],[0,5.663],[3.927,0],[0,0]],"v":[[8.231,6.244],[4.304,6.244],[-7.928,14.957],[0.68,23.088],[8.231,12.778]],"c":true},"ix":2},"nm":"Path 1","mn":"ADBE Vector Shape - Group","hd":false},{"ind":1,"ty":"sh","ix":2,"ks":{"a":0,"k":{"i":[[23.407,0],[0,16.408],[-25.37,0],[0,0],[0,0],[8.76,0],[4.53,-5.082],[0,0],[0,0],[-20.538,0],[0,-21.926],[0,0]],"o":[[-17.669,0],[0,-16.699],[0,0],[0,0],[0,-7.841],[-12.081,0],[0,0],[0,0],[0,-9.002],[19.179,0],[0,0],[0,23.523]],"v":[[-0.679,41.965],[-31.789,16.118],[4.757,-9.874],[7.778,-9.874],[7.778,-12.487],[-5.814,-22.215],[-28.768,-13.504],[-29.523,-13.504],[-29.523,-22.361],[-0.528,-41.964],[31.79,-9.002],[31.79,8.568]],"c":true},"ix":2},"nm":"Path 2","mn":"ADBE Vector Shape - Group","hd":false},{"ty":"mm","mm":1,"nm":"Merge Paths 1","mn":"ADBE Vector Filter - Merge","hd":false},{"ty":"fl","c":{"a":0,"k":[1,0.839860265395,0.169323191923,1],"ix":4},"o":{"a":0,"k":100,"ix":5},"r":1,"bm":0,"nm":"Fill 1","mn":"ADBE Vector Graphic - Fill","hd":false},{"ty":"tr","p":{"a":0,"k":[668.118,674.928],"ix":2},"a":{"a":0,"k":[0,0],"ix":1},"s":{"a":0,"k":[100,100],"ix":3},"r":{"a":0,"k":0,"ix":6},"o":{"a":0,"k":100,"ix":7},"sk":{"a":0,"k":0,"ix":4},"sa":{"a":0,"k":0,"ix":5},"nm":"Transform"}],"nm":"Group 3","np":4,"cix":2,"bm":0,"ix":3,"mn":"ADBE Vector Group","hd":false},{"ty":"gr","it":[{"ind":0,"ty":"sh","ix":1,"ks":{"a":0,"k":{"i":[[0,0],[0,9.293],[0,0],[6.644,0],[0,-12.343],[0,0],[0,0],[0,10.6],[0,0],[8.306,0],[0,-12.342],[0,0],[0,0],[0,8.712],[0,0],[-21.898,0],[-3.021,-5.953],[-10.119,0],[0,-24.394],[0,0]],"o":[[-12.384,0],[0,0],[0,-13.649],[-5.587,0],[0,0],[0,0],[-11.023,0],[0,0],[0,-9.002],[-6.796,0],[0,0],[0,0],[-10.723,0],[0,0],[0,-22.362],[11.326,0],[3.927,-5.517],[20.991,0],[0,0],[0,0]],"v":[[47.193,40.948],[30.279,26.137],[30.279,-4.211],[20.614,-20.474],[12.156,-4.792],[12.156,40.948],[4.606,40.948],[-12.157,26.137],[-12.157,-5.227],[-21.823,-20.474],[-30.43,-4.357],[-30.43,40.948],[-39.188,40.948],[-55.8,26.137],[-55.8,-4.646],[-21.67,-40.948],[0.529,-29.331],[22.88,-40.948],[55.8,-6.243],[55.8,40.948]],"c":true},"ix":2},"nm":"Path 1","mn":"ADBE Vector Shape - Group","hd":false},{"ty":"fl","c":{"a":0,"k":[1,0.839860265395,0.169323191923,1],"ix":4},"o":{"a":0,"k":100,"ix":5},"r":1,"bm":0,"nm":"Fill 1","mn":"ADBE Vector Graphic - Fill","hd":false},{"ty":"tr","p":{"a":0,"k":[568.906,673.912],"ix":2},"a":{"a":0,"k":[0,0],"ix":1},"s":{"a":0,"k":[100,100],"ix":3},"r":{"a":0,"k":0,"ix":6},"o":{"a":0,"k":100,"ix":7},"sk":{"a":0,"k":0,"ix":4},"sa":{"a":0,"k":0,"ix":5},"nm":"Transform"}],"nm":"Group 4","np":2,"cix":2,"bm":0,"ix":4,"mn":"ADBE Vector Group","hd":false},{"ty":"gr","it":[{"ind":0,"ty":"sh","ix":1,"ks":{"a":0,"k":{"i":[[7.098,0],[0,-12.923],[-7.852,0],[0,14.521]],"o":[[-6.493,0],[0,17.279],[5.588,0],[0,-18.44]],"v":[[-0.529,-21.635],[-12.007,-1.597],[0.831,21.781],[12.005,1.596]],"c":true},"ix":2},"nm":"Path 1","mn":"ADBE Vector Shape - Group","hd":false},{"ind":1,"ty":"sh","ix":2,"ks":{"a":0,"k":{"i":[[-23.105,0],[0,-25.7],[24.011,0],[0,24.395]],"o":[[21.596,0],[0,25.702],[-22.501,0],[0,-24.684]],"v":[[0.378,-41.964],[36.923,-0.581],[-0.227,41.964],[-36.923,0.726]],"c":true},"ix":2},"nm":"Path 2","mn":"ADBE Vector Shape - Group","hd":false},{"ty":"mm","mm":1,"nm":"Merge Paths 1","mn":"ADBE Vector Filter - Merge","hd":false},{"ty":"fl","c":{"a":0,"k":[1,0.839860265395,0.169323191923,1],"ix":4},"o":{"a":0,"k":100,"ix":5},"r":1,"bm":0,"nm":"Fill 1","mn":"ADBE Vector Graphic - Fill","hd":false},{"ty":"tr","p":{"a":0,"k":[464.557,674.929],"ix":2},"a":{"a":0,"k":[0,0],"ix":1},"s":{"a":0,"k":[100,100],"ix":3},"r":{"a":0,"k":0,"ix":6},"o":{"a":0,"k":100,"ix":7},"sk":{"a":0,"k":0,"ix":4},"sa":{"a":0,"k":0,"ix":5},"nm":"Transform"}],"nm":"Group 5","np":4,"cix":2,"bm":0,"ix":5,"mn":"ADBE Vector Group","hd":false},{"ty":"gr","it":[{"ind":0,"ty":"sh","ix":1,"ks":{"a":0,"k":{"i":[[7.098,0],[0,-12.923],[-7.853,0],[0,14.521]],"o":[[-6.494,0],[0,17.279],[5.588,0],[0,-18.44]],"v":[[-0.529,-21.635],[-12.005,-1.597],[0.831,21.781],[12.007,1.596]],"c":true},"ix":2},"nm":"Path 1","mn":"ADBE Vector Shape - Group","hd":false},{"ind":1,"ty":"sh","ix":2,"ks":{"a":0,"k":{"i":[[-23.105,0],[0,-25.7],[24.012,0],[0,24.395]],"o":[[21.595,0],[0,25.702],[-22.501,0],[0,-24.684]],"v":[[0.378,-41.964],[36.923,-0.581],[-0.227,41.964],[-36.923,0.726]],"c":true},"ix":2},"nm":"Path 2","mn":"ADBE Vector Shape - Group","hd":false},{"ty":"mm","mm":1,"nm":"Merge Paths 1","mn":"ADBE Vector Filter - Merge","hd":false},{"ty":"fl","c":{"a":0,"k":[1,0.839860265395,0.169323191923,1],"ix":4},"o":{"a":0,"k":100,"ix":5},"r":1,"bm":0,"nm":"Fill 1","mn":"ADBE Vector Graphic - Fill","hd":false},{"ty":"tr","p":{"a":0,"k":[381.652,674.929],"ix":2},"a":{"a":0,"k":[0,0],"ix":1},"s":{"a":0,"k":[100,100],"ix":3},"r":{"a":0,"k":0,"ix":6},"o":{"a":0,"k":100,"ix":7},"sk":{"a":0,"k":0,"ix":4},"sa":{"a":0,"k":0,"ix":5},"nm":"Transform"}],"nm":"Group 6","np":4,"cix":2,"bm":0,"ix":6,"mn":"ADBE Vector Group","hd":false},{"ty":"gr","it":[{"ind":0,"ty":"sh","ix":1,"ks":{"a":0,"k":{"i":[[6.645,0],[0,-11.326],[-5.285,0],[0,11.618]],"o":[[-6.645,0],[0,13.359],[6.796,0],[0,-12.923]],"v":[[1.208,-34.123],[-10.118,-16.263],[-0.302,0.29],[9.967,-16.554]],"c":true},"ix":2},"nm":"Path 1","mn":"ADBE Vector Shape - Group","hd":false},{"ind":1,"ty":"sh","ix":2,"ks":{"a":0,"k":{"i":[[-0.302,-4.211],[0,-1.888],[22.199,0],[0,10.745],[0,0],[0,0],[-9.966,0],[0,11.762],[0.302,1.452],[6.342,0],[0,21.055],[-22.803,0],[0,-26.136],[0,0]],"o":[[0.302,4.356],[0,23.523],[-19.179,0],[0,0],[0,0],[5.134,5.228],[10.723,0],[0,-1.452],[-2.114,5.373],[-17.971,0],[0,-23.522],[21.294,0],[0,0],[0,2.178]],"v":[[35.036,5.518],[35.338,16.553],[-1.51,54.016],[-30.203,34.994],[-30.203,26.572],[-29.146,26.572],[-5.286,33.688],[10.42,15.827],[9.967,10.164],[-3.926,20.184],[-35.338,-12.198],[2.265,-54.016],[34.734,-16.699],[34.734,-5.953]],"c":true},"ix":2},"nm":"Path 2","mn":"ADBE Vector Shape - Group","hd":false},{"ty":"mm","mm":1,"nm":"Merge Paths 1","mn":"ADBE Vector Filter - Merge","hd":false},{"ty":"fl","c":{"a":0,"k":[1,0.839860265395,0.169323191923,1],"ix":4},"o":{"a":0,"k":100,"ix":5},"r":1,"bm":0,"nm":"Fill 1","mn":"ADBE Vector Graphic - Fill","hd":false},{"ty":"tr","p":{"a":0,"k":[298.672,686.98],"ix":2},"a":{"a":0,"k":[0,0],"ix":1},"s":{"a":0,"k":[100,100],"ix":3},"r":{"a":0,"k":0,"ix":6},"o":{"a":0,"k":100,"ix":7},"sk":{"a":0,"k":0,"ix":4},"sa":{"a":0,"k":0,"ix":5},"nm":"Transform"}],"nm":"Group 7","np":4,"cix":2,"bm":0,"ix":7,"mn":"ADBE Vector Group","hd":false},{"ty":"gr","it":[{"ind":0,"ty":"sh","ix":1,"ks":{"a":0,"k":{"i":[[0,-171.208],[171.208,0],[0,171.208],[-171.208,0]],"o":[[0,171.208],[-171.208,0],[0,-171.208],[171.208,0]],"v":[[310,0],[0,310],[-310,0],[0,-310]],"c":true},"ix":2},"nm":"Path 1","mn":"ADBE Vector Shape - Group","hd":false},{"ty":"fl","c":{"a":0,"k":[0.197251742494,0.585483446308,0.287901126637,1],"ix":4},"o":{"a":0,"k":100,"ix":5},"r":1,"bm":0,"nm":"Fill 1","mn":"ADBE Vector Graphic - Fill","hd":false},{"ty":"tr","p":{"a":0,"k":[535,675],"ix":2},"a":{"a":0,"k":[0,0],"ix":1},"s":{"a":0,"k":[100,100],"ix":3},"r":{"a":0,"k":0,"ix":6},"o":{"a":0,"k":100,"ix":7},"sk":{"a":0,"k":0,"ix":4},"sa":{"a":0,"k":0,"ix":5},"nm":"Transform"}],"nm":"Group 8","np":2,"cix":2,"bm":0,"ix":8,"mn":"ADBE Vector Group","hd":false}],"ip":0,"op":250,"st":0,"bm":0},{"ddd":0,"ind":2,"ty":4,"nm":"Logo%20loading Outlines 4","sr":1,"ks":{"o":{"a":0,"k":100,"ix":11},"r":{"a":0,"k":0,"ix":10},"p":{"a":0,"k":[540,540,0],"ix":2,"l":2},"a":{"a":0,"k":[540,675,0],"ix":1,"l":2},"s":{"a":0,"k":[162,162,100],"ix":6,"l":2}},"ao":0,"shapes":[{"ty":"gr","it":[{"ind":0,"ty":"sh","ix":1,"ks":{"a":0,"k":{"i":[[0,-171.208],[171.208,0],[0,171.208],[-171.208,0]],"o":[[0,171.208],[-171.208,0],[0,-171.208],[171.208,0]],"v":[[310,0],[0,310],[-310,0],[0,-310]],"c":true},"ix":2},"nm":"Path 1","mn":"ADBE Vector Shape - Group","hd":false},{"ty":"st","c":{"a":0,"k":[0.196078446332,0.58431372549,0.286274509804,1],"ix":3},"o":{"a":0,"k":100,"ix":4},"w":{"a":0,"k":9,"ix":5},"lc":1,"lj":1,"ml":4,"bm":0,"nm":"Stroke 1","mn":"ADBE Vector Graphic - Stroke","hd":false},{"ty":"tr","p":{"a":0,"k":[535,675],"ix":2},"a":{"a":0,"k":[0,0],"ix":1},"s":{"a":0,"k":[100,100],"ix":3},"r":{"a":0,"k":0,"ix":6},"o":{"a":0,"k":100,"ix":7},"sk":{"a":0,"k":0,"ix":4},"sa":{"a":0,"k":0,"ix":5},"nm":"Transform"}],"nm":"Group 8","np":3,"cix":2,"bm":0,"ix":8,"mn":"ADBE Vector Group","hd":false},{"ty":"tm","s":{"a":1,"k":[{"i":{"x":[0.667],"y":[1]},"o":{"x":[0.333],"y":[0]},"t":8,"s":[0]},{"i":{"x":[0.833],"y":[1]},"o":{"x":[0.167],"y":[0]},"t":20.108,"s":[45]},{"t":40,"s":[100]}],"ix":1},"e":{"a":1,"k":[{"i":{"x":[0.667],"y":[1]},"o":{"x":[0.333],"y":[0]},"t":8,"s":[0]},{"i":{"x":[0.667],"y":[1]},"o":{"x":[0.333],"y":[0]},"t":23.567,"s":[40]},{"t":35.67578125,"s":[100]}],"ix":2},"o":{"a":0,"k":-91,"ix":3},"m":1,"ix":9,"nm":"Trim Paths 1","mn":"ADBE Vector Filter - Trim","hd":false}],"ip":8,"op":258,"st":8,"bm":0},{"ddd":0,"ind":3,"ty":4,"nm":"Logo%20loading Outlines 3","sr":1,"ks":{"o":{"a":0,"k":100,"ix":11},"r":{"a":0,"k":0,"ix":10},"p":{"a":0,"k":[540,540,0],"ix":2,"l":2},"a":{"a":0,"k":[540,675,0],"ix":1,"l":2},"s":{"a":0,"k":[153,153,100],"ix":6,"l":2}},"ao":0,"shapes":[{"ty":"gr","it":[{"ind":0,"ty":"sh","ix":1,"ks":{"a":0,"k":{"i":[[0,-171.208],[171.208,0],[0,171.208],[-171.208,0]],"o":[[0,171.208],[-171.208,0],[0,-171.208],[171.208,0]],"v":[[310,0],[0,310],[-310,0],[0,-310]],"c":true},"ix":2},"nm":"Path 1","mn":"ADBE Vector Shape - Group","hd":false},{"ty":"st","c":{"a":0,"k":[0.196078446332,0.58431372549,0.286274509804,1],"ix":3},"o":{"a":0,"k":100,"ix":4},"w":{"a":0,"k":9,"ix":5},"lc":1,"lj":1,"ml":4,"bm":0,"nm":"Stroke 1","mn":"ADBE Vector Graphic - Stroke","hd":false},{"ty":"tr","p":{"a":0,"k":[535,675],"ix":2},"a":{"a":0,"k":[0,0],"ix":1},"s":{"a":0,"k":[100,100],"ix":3},"r":{"a":0,"k":0,"ix":6},"o":{"a":0,"k":100,"ix":7},"sk":{"a":0,"k":0,"ix":4},"sa":{"a":0,"k":0,"ix":5},"nm":"Transform"}],"nm":"Group 8","np":3,"cix":2,"bm":0,"ix":8,"mn":"ADBE Vector Group","hd":false},{"ty":"tm","s":{"a":1,"k":[{"i":{"x":[0.667],"y":[1]},"o":{"x":[0.333],"y":[0]},"t":4,"s":[0]},{"i":{"x":[0.833],"y":[1]},"o":{"x":[0.167],"y":[0]},"t":16.486,"s":[45]},{"t":37,"s":[100]}],"ix":1},"e":{"a":1,"k":[{"i":{"x":[0.667],"y":[1]},"o":{"x":[0.333],"y":[0]},"t":4,"s":[0]},{"i":{"x":[0.667],"y":[1]},"o":{"x":[0.333],"y":[0]},"t":20.054,"s":[40]},{"t":32.541015625,"s":[100]}],"ix":2},"o":{"a":0,"k":-91,"ix":3},"m":1,"ix":9,"nm":"Trim Paths 1","mn":"ADBE Vector Filter - Trim","hd":false}],"ip":4,"op":254,"st":4,"bm":0},{"ddd":0,"ind":4,"ty":4,"nm":"Logo%20loading Outlines 2","sr":1,"ks":{"o":{"a":0,"k":100,"ix":11},"r":{"a":0,"k":0,"ix":10},"p":{"a":0,"k":[540,540,0],"ix":2,"l":2},"a":{"a":0,"k":[540,675,0],"ix":1,"l":2},"s":{"a":0,"k":[144,144,100],"ix":6,"l":2}},"ao":0,"shapes":[{"ty":"gr","it":[{"ind":0,"ty":"sh","ix":1,"ks":{"a":0,"k":{"i":[[0,-171.208],[171.208,0],[0,171.208],[-171.208,0]],"o":[[0,171.208],[-171.208,0],[0,-171.208],[171.208,0]],"v":[[310,0],[0,310],[-310,0],[0,-310]],"c":true},"ix":2},"nm":"Path 1","mn":"ADBE Vector Shape - Group","hd":false},{"ty":"st","c":{"a":0,"k":[0.196078446332,0.58431372549,0.286274509804,1],"ix":3},"o":{"a":0,"k":100,"ix":4},"w":{"a":0,"k":9,"ix":5},"lc":1,"lj":1,"ml":4,"bm":0,"nm":"Stroke 1","mn":"ADBE Vector Graphic - Stroke","hd":false},{"ty":"tr","p":{"a":0,"k":[535,675],"ix":2},"a":{"a":0,"k":[0,0],"ix":1},"s":{"a":0,"k":[100,100],"ix":3},"r":{"a":0,"k":0,"ix":6},"o":{"a":0,"k":100,"ix":7},"sk":{"a":0,"k":0,"ix":4},"sa":{"a":0,"k":0,"ix":5},"nm":"Transform"}],"nm":"Group 8","np":3,"cix":2,"bm":0,"ix":8,"mn":"ADBE Vector Group","hd":false},{"ty":"tm","s":{"a":1,"k":[{"i":{"x":[0.667],"y":[1]},"o":{"x":[0.333],"y":[0]},"t":0,"s":[0]},{"i":{"x":[0.833],"y":[1]},"o":{"x":[0.167],"y":[0]},"t":12.108,"s":[45]},{"t":32,"s":[100]}],"ix":1},"e":{"a":1,"k":[{"i":{"x":[0.667],"y":[1]},"o":{"x":[0.333],"y":[0]},"t":0,"s":[0]},{"i":{"x":[0.667],"y":[1]},"o":{"x":[0.333],"y":[0]},"t":15.567,"s":[40]},{"t":27.67578125,"s":[100]}],"ix":2},"o":{"a":0,"k":-91,"ix":3},"m":1,"ix":9,"nm":"Trim Paths 1","mn":"ADBE Vector Filter - Trim","hd":false}],"ip":0,"op":250,"st":0,"bm":0}],"markers":[]}